cloudcoil/models/velero/__init__.py
cloudcoil/models/velero/py.typed
cloudcoil/models/velero/v1.py
cloudcoil/models/velero/v2alpha1.py
cloudcoil_models_velero-1.15.2.0.dist-info/METADATA
cloudcoil_models_velero-1.15.2.0.dist-info/WHEEL
cloudcoil_models_velero-1.15.2.0.dist-info/licenses/LICENSE
cloudcoil_models_velero-1.15.2.0.dist-info/RECORD
