Metadata-Version: 2.4
Name: cloudcoil.models.velero
Version: 1.15.2.0
Summary: Versioned velero models for cloudcoil
Project-URL: Homepage, https://github.com/cloudcoil/cloudcoil
Project-URL: Documentation, https://cloudcoil.github.io/cloudcoil
Project-URL: Repository, https://github.com/cloudcoil/models-velero
Project-URL: Issues, https://github.com/cloudcoil/models-velero/issues
Project-URL: Changelog, https://github.com/cloudcoil/models-velero/releases
Author-email: Sambhav Kothari <sambhavs.email@gmail.com>
Maintainer-email: Sambhav Kothari <sambhavs.email@gmail.com>
License: Apache-2.0
License-File: LICENSE
Keywords: async,cloud-native,cloudcoil,cloudcoil-models,kubernetes,pydantic,python,velero
Classifier: Programming Language :: Python :: 3.10
Classifier: Programming Language :: Python :: 3.11
Classifier: Programming Language :: Python :: 3.12
Classifier: Programming Language :: Python :: 3.13
Requires-Python: >=3.10
Requires-Dist: cloudcoil>=0.4.0
